cqu_kb/__init__.py
cqu_kb/__main__.py
cqu_kb/utils.py
cqu_kb/version.py
cqu_kb/config/__init__.py
cqu_kb/config/config.py
cqu_kb/config/config_default.yaml
cqu_kb/core/KBCore.py
cqu_kb/core/KBCoreGrad.py
cqu_kb/core/KBCoreUnderGrad.py
cqu_kb/core/__init__.py
cqu_kb-0.3.0.dist-info/LICENSE
cqu_kb-0.3.0.dist-info/METADATA
cqu_kb-0.3.0.dist-info/WHEEL
cqu_kb-0.3.0.dist-info/entry_points.txt
cqu_kb-0.3.0.dist-info/top_level.txt
cqu_kb-0.3.0.dist-info/RECORD
