Metadata-Version: 2.1
Name: cqu-kb
Version: 0.3.0
Summary: 一个导出重庆大学课程表的第三方工具
Home-page: https://github.com/CQU-AI/cqu-kb
Author: CQU-AI
Author-email: peter@mail.loopy.tech
License: GPL License
Platform: all
Requires-Python: >=3.6
Requires-Dist: PyYAML (~=5.3.1)
Requires-Dist: requests (~=2.24.0)
Requires-Dist: pytz (~=2020.1)
Requires-Dist: cqu-jxgl (>=0.2.0)
Requires-Dist: icalendar (~=4.0.6)
Requires-Dist: beautifulsoup4 (~=4.9.1)
